{
  "BUILD_REPO_OWNER": "matheusd",
  "BUILD_REPO_REPO": "decred-weekly-builds",
  "DECRED_REPO_OWNER": "decred",
  "dcrdBranch": null,
  "dcrdRepoOwner": "decred",
  "dcrwBranch": null,
  "dcrwRepoOwner": "decred",
  "decreditonBranch": "animation-poc",
  "decreditonRepoOwner": "matheusd",
  "shaDcrd": "ca7eeee6af72d69a73fe339b453c1ca20d211d04",
  "shaDcrwallet": "69603e2d6d62eefe34f94dc245fc8f8f9180a57c",
  "shaDecrediton": "8167018c6c9dd21d5a7fbe9de51efbe02868f016",
  "tagName": "v20180614143940",
  "version": "20180614143940"
}